impfic_core/__init__.py
impfic_core/analysis/prep_word2vec_emotion_recognition.py
impfic_core/api.py
impfic_core/extract/extract_stats.py
impfic_core/fetch/fetch_elastic.py
impfic_core/map/map_genre.py
impfic_core/map/map_isbns.py
impfic_core/measures/__init__.py
impfic_core/measures/dispersion.py
impfic_core/measures/fractality.py
impfic_core/measures/keyness.py
impfic_core/measures/length.py
impfic_core/measures/temp.py
impfic_core/measures/text_features.py
impfic_core/parse/__init__.py
impfic_core/parse/book_model.py
impfic_core/parse/chunk.py
impfic_core/parse/doc.py
impfic_core/parse/parse_alpino_sentence.py
impfic_core/parse/parse_book_metadata.py
impfic_core/parse/parse_epub.py
impfic_core/parse/parse_review.py
impfic_core/parse/parse_trankit_sentence.py
impfic_core/parse/pronouns.py
impfic_core/parse/sentence.py
impfic_core/pattern/__init__.py
impfic_core/pattern/patterns.py
impfic_core/pattern/patterns_nl.py
impfic_core/pattern/tag_sets.py
impfic_core/pattern/tag_sets_de.py
impfic_core/pattern/tag_sets_en.py
impfic_core/pattern/tag_sets_nl.py
impfic_core/plot/plot.py
impfic_core/resources/rbn.py
impfic_core/secrets_example.py
impfic_core-0.12.0.dist-info/METADATA
impfic_core-0.12.0.dist-info/WHEEL
impfic_core-0.12.0.dist-info/entry_points.txt
impfic_core-0.12.0.dist-info/RECORD
