Metadata-Version: 2.4
Name: impfic-core
Version: 0.12.0
Summary: Utility functions for the Impact and Fiction project
License: MIT
Author: Marijn Koolen
Author-email: marijn.koolen@huygens.knaw.nl
Requires-Python: >=3.8,<=3.12
Classifier: Development Status :: 4 - Beta
Classifier: Intended Audience :: Science/Research
Classifier: License :: OSI Approved :: MIT License
Classifier: Operating System :: OS Independent
Classifier: Programming Language :: Python :: 3
Classifier: Programming Language :: Python :: 3.8
Classifier: Programming Language :: Python :: 3.9
Classifier: Programming Language :: Python :: 3.10
Classifier: Programming Language :: Python :: 3.11
Classifier: Programming Language :: Python :: 3.12
Classifier: Topic :: Scientific/Engineering
Requires-Dist: numpy
Requires-Dist: pandas
Project-URL: Bug Tracker, https://github.com/impact-and-fiction/impfic-core/issues
Project-URL: Homepage, https://github.com/impact-and-fiction/impfic-core
Project-URL: Repository, https://github.com/impact-and-fiction/impfic-core
